ChromiumZhongwenWendang/README.md
ChromiumZhongwenWendang/__init__.py
ChromiumZhongwenWendang/__main__.py
ChromiumZhongwenWendang/file.epub
ChromiumZhongwenWendang/index.html
ChromiumZhongwenWendang/css/__init__.py
ChromiumZhongwenWendang/css/annotations.css
ChromiumZhongwenWendang/css/main.css
ChromiumZhongwenWendang/css/normalize.css
ChromiumZhongwenWendang/css/popup.css
ChromiumZhongwenWendang/font/__init__.py
ChromiumZhongwenWendang/font/fontello.eot
ChromiumZhongwenWendang/font/fontello.svg
ChromiumZhongwenWendang/font/fontello.ttf
ChromiumZhongwenWendang/font/fontello.woff
ChromiumZhongwenWendang/img/__init__.py
ChromiumZhongwenWendang/img/annotator-glyph-sprite.png
ChromiumZhongwenWendang/img/annotator-icon-sprite.png
ChromiumZhongwenWendang/img/apple-touch-icon.png
ChromiumZhongwenWendang/img/cancelfullscreen.png
ChromiumZhongwenWendang/img/close.png
ChromiumZhongwenWendang/img/fullscreen.png
ChromiumZhongwenWendang/img/loader.gif
ChromiumZhongwenWendang/img/menu-icon.png
ChromiumZhongwenWendang/img/save.png
ChromiumZhongwenWendang/img/saved.png
ChromiumZhongwenWendang/img/settings-s.png
ChromiumZhongwenWendang/img/settings.png
ChromiumZhongwenWendang/img/star.png
ChromiumZhongwenWendang/js/__init__.py
ChromiumZhongwenWendang/js/epub.js
ChromiumZhongwenWendang/js/epub.min.js
ChromiumZhongwenWendang/js/epub.min.map
ChromiumZhongwenWendang/js/hooks.min.js
ChromiumZhongwenWendang/js/hooks.min.map
ChromiumZhongwenWendang/js/reader.js
ChromiumZhongwenWendang/js/reader.js.map
ChromiumZhongwenWendang/js/reader.min.js
ChromiumZhongwenWendang/js/reader.min.map
ChromiumZhongwenWendang/js/hooks/__init__.py
ChromiumZhongwenWendang/js/hooks/extensions/__init__.py
ChromiumZhongwenWendang/js/hooks/extensions/highlight.js
ChromiumZhongwenWendang/js/libs/__init__.py
ChromiumZhongwenWendang/js/libs/jquery.min.js
ChromiumZhongwenWendang/js/libs/localforage.min.js
ChromiumZhongwenWendang/js/libs/screenfull.js
ChromiumZhongwenWendang/js/libs/screenfull.min.js
chromium_zhongwen_wendang-2024.3.3.0.dist-info/METADATA
chromium_zhongwen_wendang-2024.3.3.0.dist-info/WHEEL
chromium_zhongwen_wendang-2024.3.3.0.dist-info/entry_points.txt
chromium_zhongwen_wendang-2024.3.3.0.dist-info/top_level.txt
chromium_zhongwen_wendang-2024.3.3.0.dist-info/RECORD
